Metadata-Version: 2.1
Name: itd
Version: 0.1.1
Summary: In The Dark - An Adventure / Escape Game for python programers.
Home-page: https://gitlab.com/dee909/itd
Author: Damien "dee" Coureau
Author-email: dee909@gmail.com
License: LGPLv3+
Keywords: game escape adventure codegame
Platform: UNKNOWN
Classifier: Development Status :: 3 - Alpha
Classifier: Operating System :: OS Independent
Classifier: Programming Language :: Python :: 2.7
Classifier: Programming Language :: Python :: 3.7
Classifier: License :: OSI Approved :: GNU Lesser General Public License v3 or later (LGPLv3+)
Requires-Python: >=2.7,!=3.0.*,!=3.1.*,!=3.2.*
